primos.py
NUM_PRIMOSJUAN-0.0.1.dist-info/METADATA
NUM_PRIMOSJUAN-0.0.1.dist-info/WHEEL
NUM_PRIMOSJUAN-0.0.1.dist-info/top_level.txt
NUM_PRIMOSJUAN-0.0.1.dist-info/RECORD
