Metadata-Version: 2.1
Name: NUM-PRIMOSJUAN
Version: 0.0.1
Summary: Ejemplo de como crear un paquete NUM_PRIMOS
Author-email: xxx <xxx@gmail.com>
Project-URL: Homepage, https://github.com/albertorc87/subir-paquete-pypi
Project-URL: Bug Tracker, https://github.com/albertorc87/subir-paquete-pypi/issues
Classifier: Programming Language :: Python :: 3
Classifier: License :: OSI Approved :: MIT License
Classifier: Operating System :: OS Independent
Requires-Python: >=3.9
